argmanager/argmanager.py
argmanager/__init__.py
argmanager-0.0.2.dist-info/METADATA
argmanager-0.0.2.dist-info/top_level.txt
argmanager-0.0.2.dist-info/RECORD
argmanager-0.0.2.dist-info/metadata.json
argmanager-0.0.2.dist-info/DESCRIPTION.rst
argmanager-0.0.2.dist-info/WHEEL
